setup.py
flexirest/__init__.py
flexirest/defaults.py
flexirest/main.py
flexirest/meta.py
flexirest/rendering.py
flexirest/tex.py
flexirest/util.py
flexirest.egg-info/PKG-INFO
flexirest.egg-info/SOURCES.txt
flexirest.egg-info/dependency_links.txt
flexirest.egg-info/entry_points.txt
flexirest.egg-info/requires.txt
flexirest.egg-info/top_level.txt
test/test_main_integration.py