Metadata-Version: 1.0
Name: flexirest
Version: 0.8.2
Summary: The medium-featured, flexible reStructuredText utility
Home-page: http://www.aspektratio.net/flexirest
Author: Jacob Oscarson
Author-email: jacob@aspektratio.net
License: GNU LGPL
Platform: UNKNOWN
Classifier: Development Status :: 4 - Beta
Classifier: License :: OSI Approved :: GNU Library or Lesser General Public License (LGPL)
Classifier: Operating System :: OS Independent
Classifier: Programming Language :: Python
Classifier: Environment :: Console
Classifier: Topic :: Documentation
Classifier: Topic :: Software Development :: Documentation
Classifier: Topic :: Text Processing :: Markup
